locuplot/__init__.py
locuplot/__main__.py
locuplot/argument_parser.py
locuplot/dto/argument.py
locuplot/helpers/fs.py
locuplot/helpers/plot.py
locuplot/locust/failures.py
locuplot/locust/generic.py
locuplot/locust/history_stats.py
locuplot/locust/stats.py
locuplot/main.py
locuplot/templates/template.html
locuplot-0.1.3.dist-info/entry_points.txt
locuplot-0.1.3.dist-info/WHEEL
locuplot-0.1.3.dist-info/METADATA
locuplot-0.1.3.dist-info/RECORD
